rabbitstore/__init__.py
rabbitstore/rabbitstore.py
rabbitstore-0.1.0.dist-info/LICENSE
rabbitstore-0.1.0.dist-info/METADATA
rabbitstore-0.1.0.dist-info/WHEEL
rabbitstore-0.1.0.dist-info/top_level.txt
rabbitstore-0.1.0.dist-info/RECORD
