Metadata-Version: 2.1
Name: rabbitstore
Version: 0.1.0
Summary: A module for storing key-value pairs using RabbitMQ
Home-page: https://github.com/yourusername/rabbitstore
Author: Your Name
Author-email: your.email@example.com
Classifier: Programming Language :: Python :: 3
Classifier: License :: OSI Approved :: MIT License
Classifier: Operating System :: OS Independent
Requires-Python: >=3.6
License-File: LICENSE
Requires-Dist: pika
